colorAw/__init__.py
colorAw/color.py
colorAw-0.0.2.dist-info/LICENCE
colorAw-0.0.2.dist-info/METADATA
colorAw-0.0.2.dist-info/WHEEL
colorAw-0.0.2.dist-info/top_level.txt
colorAw-0.0.2.dist-info/RECORD
